{
    "packages": {
        "smtest\/smtest": {
            "dev-master": {
                "name": "smtest\/smtest",
                "type": "project",
		"minimum-stability": "stable",
                "source": {
                    "url": "https://github.com/Mail4car/testc.git",
                    "type": "git",
		    "reference": "547a1c403ec3a025dd9e04ea5a4c6411353fb6f9"
                },
                "homepage": "http://oft-e.com",
                "version": "1.0.0-stable"
            }
        },
	"smtest\/pr": {
            "dev-master": {
                "name": "smtest\/pr",
                "type": "project",
		"minimum-stability": "stable",
                "source": {
                    "url": "https://github.com/Mail4car/pr.git",
                    "type": "git",
		    "reference": "2d0a85626c891ffe40fbabfa6ed8ae926838a991"
                },
		"require": {
			"smtest/smtest": "*"
		},
                "homepage": "http://oft-e.com",
                "version": "1.0.0-stable"
            }
        }
    }
}
